springheel_jacky/__init__.py
springheel_jacky/__main__.py
springheel_jacky/categories.py
springheel_jacky/cbz.py
springheel_jacky/chapters.py
springheel_jacky/cli.py
springheel_jacky/images.py
springheel_jacky/internet.py
springheel_jacky/links.py
springheel_jacky/search.py
springheel_jacky/strips.py
springheel_jacky/tests.py
springheel_jacky-1.0.data/data/share/man/man1/springheel_jacky.1.gz
springheel_jacky-1.0.dist-info/AUTHORS
springheel_jacky-1.0.dist-info/LICENSE
springheel_jacky-1.0.dist-info/METADATA
springheel_jacky-1.0.dist-info/WHEEL
springheel_jacky-1.0.dist-info/entry_points.txt
springheel_jacky-1.0.dist-info/top_level.txt
springheel_jacky-1.0.dist-info/RECORD
