Metadata-Version: 2.1
Name: springheel-jacky
Version: 1.0
Summary: Library and command-line interface for Springheel sites
Home-page: https://www.twinkle-night.net/Code/springheel_jacky.html
Author: Garrick
Author-email: earthisthering@posteo.de
License: GPLv3+
Keywords: website,webcomic,static
Platform: UNKNOWN
Classifier: Development Status :: 4 - Beta
Classifier: License :: OSI Approved :: GNU General Public License v3 or later (GPLv3+)
Classifier: Programming Language :: Python :: 3
Classifier: Intended Audience :: End Users/Desktop
Requires-Dist: requests
Requires-Dist: html-text
Provides-Extra: docs
Requires-Dist: sphinx (>=3.4.1) ; extra == 'docs'
Requires-Dist: numpydoc ; extra == 'docs'
